client/__init__.py
client/client_start.py
client/custom/__init__.py
client/custom/decorators.py
client/custom/errors.py
client/custom/function.py
client/custom/metaclass.py
client/custom/parse_args.py
client/custom/transport.py
client/custom/variables.py
client/database/__init__.py
client/database/database.py
client/gui/__init__.py
client/gui/add_contact.py
client/gui/delete_contact.py
client/gui/main_window.py
client/gui/main_window_gui.py
client/gui/start_menu.py
client/log/__init__.py
client/log/log_config.py
client/log/log_variables.py
Messenger_Desktop_Client_Application-0.7.dist-info/METADATA
Messenger_Desktop_Client_Application-0.7.dist-info/WHEEL
Messenger_Desktop_Client_Application-0.7.dist-info/top_level.txt
Messenger_Desktop_Client_Application-0.7.dist-info/RECORD
