Metadata-Version: 2.1
Name: Messenger-Desktop-Client-Application
Version: 0.7
Summary: Messenger_Client
Home-page: UNKNOWN
Author: Dronkin Artem
Author-email: adronkin@gmail.com
License: UNKNOWN
Platform: UNKNOWN
Requires-Dist: PyQt5
Requires-Dist: sqlalchemy
Requires-Dist: pycryptodome
Requires-Dist: functools
